vibepy/__init__.py
vibepy/cli.py
vibepy/codeblock.py
vibepy/main.py
vibepy/run.py
vibepy-0.2.4.dist-info/METADATA
vibepy-0.2.4.dist-info/WHEEL
vibepy-0.2.4.dist-info/entry_points.txt
vibepy-0.2.4.dist-info/top_level.txt
vibepy-0.2.4.dist-info/RECORD
