Metadata-Version: 2.4
Name: vibepy
Version: 0.2.4
Summary: have your terminal talking to and running codes from open-ai
Author-email: brainfo <scilavisher@example.com>
License-Expression: MIT
Project-URL: Homepage, https://github.com/brainfo/vibepy
Classifier: Programming Language :: Python :: 3
Classifier: Programming Language :: Python :: 3.10
Classifier: Operating System :: OS Independent
Requires-Python: <3.11,>=3.10
Requires-Dist: readchar>=3.0.0
Requires-Dist: openai>=1.0.0
Requires-Dist: requests<3.0.0,>=2.31.0
Requires-Dist: colorama>=0.4.6
Requires-Dist: pyperclip>=1.8.0
Provides-Extra: dev
Requires-Dist: pytest>=7.0.0; extra == "dev"
Requires-Dist: pytest-cov>=4.0.0; extra == "dev"
Requires-Dist: flake8>=6.0.0; extra == "dev"
